{"changes": [{"time": 0, "bw": 4.521432, "rtt": 66.8, "loss": 0.0}, {"time": 30, "bw": 2.251856, "rtt": 34.961, "loss": 0.0}, {"time": 60, "bw": 1.313176, "rtt": 63.722, "loss": 0.0}, {"time": 90, "bw": 3.192952, "rtt": 21.43, "loss": 0.0}, {"time": 120, "bw": 2.68292, "rtt": 28.022, "loss": 0.0}, {"time": 150, "bw": 3.55684, "rtt": 47.844, "loss": 0.0}, {"time": 180, "bw": 2.711304, "rtt": 34.642, "loss": 0.0}, {"time": 210, "bw": 4.327472, "rtt": 17.217, "loss": 0.0}], "repeat": "True", "pause": 30, "duration": 640}