{"changes": [{"time": 0, "bw": 5.666336, "rtt": 33.755, "loss": 0.0}, {"time": 30, "bw": 5.33012, "rtt": 16.087, "loss": 0.0}, {"time": 60, "bw": 3.695768, "rtt": 20.513, "loss": 0.0}, {"time": 90, "bw": 8.799648, "rtt": 13.13, "loss": 0.0}, {"time": 120, "bw": 2.828888, "rtt": 14.978, "loss": 0.0}, {"time": 150, "bw": 5.996376, "rtt": 17.433, "loss": 0.0}, {"time": 180, "bw": 5.778768, "rtt": 13.337, "loss": 0.0}, {"time": 210, "bw": 5.352704, "rtt": 13.259, "loss": 0.0}], "repeat": "True", "pause": 30, "duration": 640}