{"changes": [{"time": 0, "bw": 6.559696, "rtt": 11.543, "loss": 0.0}, {"time": 30, "bw": 6.882976, "rtt": 13.055, "loss": 0.0}, {"time": 60, "bw": 4.787192, "rtt": 11.249, "loss": 0.0}, {"time": 90, "bw": 5.743072, "rtt": 0.0, "loss": 0.0}, {"time": 120, "bw": 7.616984, "rtt": 16.727, "loss": 0.0}, {"time": 150, "bw": 9.618064, "rtt": 11.642, "loss": 0.0}, {"time": 180, "bw": 7.181304, "rtt": 10.889, "loss": 0.0}, {"time": 210, "bw": 5.131024, "rtt": 12.293, "loss": 0.0}], "repeat": "True", "pause": 30, "duration": 640}